{
  "rex91320@gmail.com": [
    {
      "file_id": "4667235588aab2a7",
      "dataset_name": "ecommerce_customer_behavior_dataset_v2.csv",
      "analyzed_at": "2026-05-05T17:07:58.449094",
      "summary": {
        "total_revenue": 21779052.59,
        "average_order_value": 1277.4387113613702,
        "unique_customers": 5000,
        "total_orders": 17049
      },
      "capabilities": {
        "kpis": {
          "status": "completed",
          "missing_columns": []
        },
        "trends": {
          "status": "completed",
          "missing_columns": []
        },
        "top_categories": {
          "status": "completed",
          "missing_columns": []
        },
        "segmentation": {
          "status": "completed",
          "missing_columns": []
        },
        "forecast": {
          "status": "completed",
          "missing_columns": []
        },
        "churn_prediction": {
          "status": "completed",
          "missing_columns": []
        }
      }
    },
    {
      "file_id": "4667235588aab2a7",
      "dataset_name": "ecommerce_customer_behavior_dataset_v2.csv",
      "analyzed_at": "2026-05-05T17:07:58.370096",
      "summary": {
        "total_revenue": 21779052.59,
        "average_order_value": 1277.4387113613702,
        "unique_customers": 5000,
        "total_orders": 17049
      },
      "capabilities": {
        "kpis": {
          "status": "completed",
          "missing_columns": []
        },
        "trends": {
          "status": "completed",
          "missing_columns": []
        },
        "top_categories": {
          "status": "completed",
          "missing_columns": []
        },
        "segmentation": {
          "status": "completed",
          "missing_columns": []
        },
        "forecast": {
          "status": "completed",
          "missing_columns": []
        },
        "churn_prediction": {
          "status": "completed",
          "missing_columns": []
        }
      }
    },
    {
      "file_id": "a20e9df3b8737dfa",
      "dataset_name": "ecommerce_customer_behavior_dataset_v2.csv",
      "analyzed_at": "2026-05-05T17:03:26.666512",
      "summary": {
        "total_revenue": 21779052.59,
        "average_order_value": 1277.4387113613702,
        "unique_customers": 5000,
        "total_orders": 17049
      },
      "capabilities": {
        "kpis": {
          "status": "completed",
          "missing_columns": []
        },
        "trends": {
          "status": "completed",
          "missing_columns": []
        },
        "top_categories": {
          "status": "completed",
          "missing_columns": []
        },
        "segmentation": {
          "status": "completed",
          "missing_columns": []
        },
        "forecast": {
          "status": "completed",
          "missing_columns": []
        },
        "churn_prediction": {
          "status": "completed",
          "missing_columns": []
        }
      }
    },
    {
      "file_id": "a20e9df3b8737dfa",
      "dataset_name": "ecommerce_customer_behavior_dataset_v2.csv",
      "analyzed_at": "2026-05-05T17:03:26.563332",
      "summary": {
        "total_revenue": 21779052.59,
        "average_order_value": 1277.4387113613702,
        "unique_customers": 5000,
        "total_orders": 17049
      },
      "capabilities": {
        "kpis": {
          "status": "completed",
          "missing_columns": []
        },
        "trends": {
          "status": "completed",
          "missing_columns": []
        },
        "top_categories": {
          "status": "completed",
          "missing_columns": []
        },
        "segmentation": {
          "status": "completed",
          "missing_columns": []
        },
        "forecast": {
          "status": "completed",
          "missing_columns": []
        },
        "churn_prediction": {
          "status": "completed",
          "missing_columns": []
        }
      }
    },
    {
      "file_id": "11fe24f9605766a8",
      "dataset_name": "ecommerce_customer_behavior_dataset_v2.csv",
      "analyzed_at": "2026-05-05T16:57:40.898843",
      "summary": {
        "total_revenue": 21779052.59,
        "average_order_value": 1277.4387113613702,
        "unique_customers": 5000,
        "total_orders": 17049
      },
      "capabilities": {
        "kpis": {
          "status": "completed",
          "missing_columns": []
        },
        "trends": {
          "status": "completed",
          "missing_columns": []
        },
        "top_categories": {
          "status": "completed",
          "missing_columns": []
        },
        "segmentation": {
          "status": "completed",
          "missing_columns": []
        },
        "forecast": {
          "status": "completed",
          "missing_columns": []
        },
        "churn_prediction": {
          "status": "completed",
          "missing_columns": []
        }
      }
    }
  ]
}